README.md
setup.py
confirma/__init__.py
confirma.egg-info/PKG-INFO
confirma.egg-info/SOURCES.txt
confirma.egg-info/dependency_links.txt
confirma.egg-info/requires.txt
confirma.egg-info/top_level.txt