Metadata-Version: 2.1
Name: confirma
Version: 0.2.2
Summary: Send Documents to ConFirma service
Home-page: https://github.com/gisce/confirma
Author: GISCE-TI, S.L.
Author-email: devel@gisce.net
License: MIT
